paulify/__init__.py
paulify/cli.py
paulify-0.1.3.dist-info/METADATA
paulify-0.1.3.dist-info/WHEEL
paulify-0.1.3.dist-info/entry_points.txt
paulify-0.1.3.dist-info/top_level.txt
paulify-0.1.3.dist-info/RECORD
