Metadata-Version: 2.4
Name: paulify
Version: 0.1.3
Summary: PAUL v1.1 license attribution helper
Author: Marty L. Danish (cactusflatscoder)
Author-email: Hello@MartyDoesData.com
Classifier: Programming Language :: Python :: 3
Classifier: License :: Other/Proprietary License
Classifier: Operating System :: OS Independent
Requires-Python: >=3.6
Dynamic: author
Dynamic: author-email
Dynamic: classifier
Dynamic: description
Dynamic: description-content-type
Dynamic: requires-python
Dynamic: summary
